TimeanddateScrapper/__init__.py
TimeanddateScrapper/worldweather.py
TimeanddateScrapper-0.0.5.dist-info/METADATA
TimeanddateScrapper-0.0.5.dist-info/WHEEL
TimeanddateScrapper-0.0.5.dist-info/top_level.txt
TimeanddateScrapper-0.0.5.dist-info/RECORD
