Metadata-Version: 2.1
Name: TimeanddateScrapper
Version: 0.0.5
Summary: The Weather Data Scrap Application extracts weather data from the popular website timeanddate.com.
Home-page: https://github.com/Bibhash7/Weather-Data-Scrap-WWDS
Author: Bibhash Ghosh
Author-email: bibhashghosh994@gmail.com
Project-URL: Bug Tracker, https://github.com/Bibhash7/Weather-Data-Scrap-WWDS/issues
Classifier: Programming Language :: Python :: 3
Classifier: License :: OSI Approved :: MIT License
Classifier: Operating System :: OS Independent
Requires-Python: >=3.6
